qcsuper/__init__.py
qcsuper/__main__.py
qcsuper/main.py
qcsuper/inputs/_base_input.py
qcsuper/inputs/_hdlc_mixin.py
qcsuper/inputs/adb.py
qcsuper/inputs/adb_wsl2.py
qcsuper/inputs/dlf_read.py
qcsuper/inputs/json_geo_read.py
qcsuper/inputs/usb_modem_argparser.py
qcsuper/inputs/usb_modem_pyserial.py
qcsuper/inputs/usb_modem_pyusb.py
qcsuper/inputs/usb_modem_pyusb_devfinder.py
qcsuper/inputs/adb_bridge/Makefile
qcsuper/inputs/adb_bridge/README.md
qcsuper/inputs/adb_bridge/adb_bridge
qcsuper/inputs/adb_bridge/adb_bridge.c
qcsuper/inputs/adb_wsl2_bridge/README.md
qcsuper/inputs/adb_wsl2_bridge/adb_wsl2_bridge.ps1
qcsuper/inputs/external/README.md
qcsuper/inputs/external/update_tools.sh
qcsuper/inputs/external/adb/AdbWinApi.dll
qcsuper/inputs/external/adb/AdbWinUsbApi.dll
qcsuper/inputs/external/adb/adb_linux
qcsuper/inputs/external/adb/adb_macos
qcsuper/inputs/external/adb/adb_windows.exe
qcsuper/inputs/external/adb/lib64/libc++.dylib
qcsuper/modules/_enable_log_mixin.py
qcsuper/modules/_utils.py
qcsuper/modules/cli.py
qcsuper/modules/decoded_sibs_dump.py
qcsuper/modules/dlf_dump.py
qcsuper/modules/efs_shell.py
qcsuper/modules/info.py
qcsuper/modules/json_geo_dump.py
qcsuper/modules/memory_dump.py
qcsuper/modules/pcap_dump.py
qcsuper/modules/efs_shell_commands/_base_efs_shell_command.py
qcsuper/modules/efs_shell_commands/cat.py
qcsuper/modules/efs_shell_commands/chmod.py
qcsuper/modules/efs_shell_commands/device_info.py
qcsuper/modules/efs_shell_commands/get.py
qcsuper/modules/efs_shell_commands/ln.py
qcsuper/modules/efs_shell_commands/ls.py
qcsuper/modules/efs_shell_commands/md5sum.py
qcsuper/modules/efs_shell_commands/mkdir.py
qcsuper/modules/efs_shell_commands/mv.py
qcsuper/modules/efs_shell_commands/put.py
qcsuper/modules/efs_shell_commands/rm.py
qcsuper/modules/efs_shell_commands/stat.py
qcsuper/protocol/efs2.py
qcsuper/protocol/gsmtap.py
qcsuper/protocol/log_types.py
qcsuper/protocol/messages.py
qcsuper/protocol/subsystems.py
qcsuper-2.0.1.dist-info/LICENSE
qcsuper-2.0.1.dist-info/METADATA
qcsuper-2.0.1.dist-info/WHEEL
qcsuper-2.0.1.dist-info/entry_points.txt
qcsuper-2.0.1.dist-info/top_level.txt
qcsuper-2.0.1.dist-info/RECORD
