Metadata-Version: 2.1
Name: qcsuper
Version: 2.0.1
Summary: QCSuper is a tool communicating with Qualcomm-based phones and modems, allowing to capture raw 2G/3G/4G radio frames, among other things
Home-page: https://github.com/P1sec/QCSuper
Author: P1 Security - Marin Moulinier
Author-email: 
Requires: pyserial(>=3.5)
Requires: pyusb(>=1.2.1)
Requires: crcmod(>=1.7)
Requires: pycrate(>=0.7.0)
License-File: LICENSE
